docschat/__init__.py
docschat/__main__.py
docschat/app.py
DocsChat-5.0.0.dist-info/LICENSE
DocsChat-5.0.0.dist-info/METADATA
DocsChat-5.0.0.dist-info/WHEEL
DocsChat-5.0.0.dist-info/entry_points.txt
DocsChat-5.0.0.dist-info/top_level.txt
DocsChat-5.0.0.dist-info/RECORD
