Metadata-Version: 2.1
Name: DocsChat
Version: 5.0.0
Summary: Chat with your docs using langchain in a streamlit app with mistral or llama in ollama.
Home-page: https://github.com/flojud/DocsChat
Author: flojud
Author-email: dev.flojud@gmail.com
License: MIT
Project-URL: Bug Tracker, https://github.com/flojud/DocsChat/issues
Keywords: llama,mistral,chat,streamlit,langchain,talk2docs
Requires-Python: >=3.10
License-File: LICENSE
Requires-Dist: streamlit
Requires-Dist: langchain ==0.1.19
Requires-Dist: langchain-chroma ==0.1.0
Requires-Dist: langchain-community ==0.0.38
Requires-Dist: langchain-experimental ==0.0.58
Requires-Dist: stqdm
Requires-Dist: watchdog
Requires-Dist: pypdf
